[
  {
    "county_metadata": {
      "state": "OK",
      "county": "Cleveland",
      "fips_code": "40021",
      "formed_year": 1907,
      "parent_county": "Oklahoma Territory",
      "grandparent_county": null,
      "county_seat": "Norman",
      "is_burned_county": false,
      "record_losses": null,
      "jurisdictional_notes": "Oklahoma Territory jurisdiction. Unassigned Lands.",
      "research_tips": "Land Run records (1889). County records from 1907.",
      "rod_online_url": "https://www.clevelandcountyclerk.org/",
      "rod_earliest_deed_year": 1907,
      "rod_online_scope": "Deeds from 1907 forward",
      "heritage_book": null
    },
    "source_profiles": [
      {
        "state": "OK",
        "county": "Cleveland",
        "record_type": "deed",
        "source_name": "Cleveland County Deed Records",
        "repository": "Cleveland County Clerk",
        "access_method": "in_person",
        "url": null,
        "year_start": 1907,
        "year_end": 2024,
        "coverage_notes": "Deeds from statehood",
        "survival_notes": null,
        "kinlore_priority": 1,
        "programmatic_access": null
      },
      {
        "state": "OK",
        "county": "Cleveland",
        "record_type": "will",
        "source_name": "Cleveland County Probate Records",
        "repository": "Cleveland County Clerk",
        "access_method": "in_person",
        "url": null,
        "year_start": 1907,
        "year_end": 2024,
        "coverage_notes": "Wills and estate records",
        "survival_notes": null,
        "kinlore_priority": 1,
        "programmatic_access": "FamilySearch API"
      },
      {
        "state": "OK",
        "county": "Cleveland",
        "record_type": "land_grant",
        "source_name": "Oklahoma Land Run Records (1889)",
        "repository": "Oklahoma Historical Society",
        "access_method": "web_free",
        "url": "https://okhistory.org/research/landrun",
        "year_start": 1889,
        "year_end": 1889,
        "coverage_notes": "Land Run claims for Oklahoma Territory",
        "survival_notes": null,
        "kinlore_priority": 2,
        "programmatic_access": null
      },
      {
        "state": "OK",
        "county": "Cleveland",
        "record_type": "marriage",
        "source_name": "Cleveland County Marriage Records",
        "repository": "Cleveland County Clerk",
        "access_method": "in_person",
        "url": null,
        "year_start": 1907,
        "year_end": 2024,
        "coverage_notes": "Marriage licenses from statehood",
        "survival_notes": null,
        "kinlore_priority": 1,
        "programmatic_access": "FamilySearch API"
      },
      {
        "state": "OK",
        "county": "Cleveland",
        "record_type": "census",
        "source_name": "1900 Census - Oklahoma Territory",
        "repository": "FamilySearch / Ancestry",
        "access_method": "web_subscription",
        "url": "https://www.familysearch.org",
        "year_start": 1900,
        "year_end": 1900,
        "coverage_notes": "Pre-statehood census",
        "survival_notes": null,
        "kinlore_priority": 2,
        "programmatic_access": "FamilySearch API"
      },
      {
        "state": "OK",
        "county": "Cleveland",
        "record_type": "birth_death",
        "source_name": "Cleveland County Vital Records",
        "repository": "Oklahoma State Department of Health",
        "access_method": "web_subscription",
        "url": "https://www.ok.gov/health/",
        "year_start": 1908,
        "year_end": 1924,
        "coverage_notes": "Early vital records",
        "survival_notes": "Incomplete coverage",
        "kinlore_priority": 2,
        "programmatic_access": null
      }
    ]
  },
  {
    "county_metadata": {
      "state": "OK",
      "county": "Coal",
      "fips_code": "40023",
      "formed_year": 1907,
      "parent_county": "Indian Territory (Choctaw Nation)",
      "grandparent_county": null,
      "county_seat": "Coalgate",
      "is_burned_county": false,
      "record_losses": null,
      "jurisdictional_notes": "Choctaw Nation jurisdiction. Dawes Rolls (Choctaw) apply.",
      "research_tips": "Choctaw Dawes Rolls at OHS. County records from 1907.",
      "rod_online_url": null,
      "rod_earliest_deed_year": 1907,
      "rod_online_scope": "Deeds from 1907 forward",
      "heritage_book": null
    },
    "source_profiles": [
      {
        "state": "OK",
        "county": "Coal",
        "record_type": "deed",
        "source_name": "Coal County Deed Records",
        "repository": "Coal County Clerk",
        "access_method": "in_person",
        "url": null,
        "year_start": 1907,
        "year_end": 2024,
        "coverage_notes": "Deeds from statehood",
        "survival_notes": null,
        "kinlore_priority": 1,
        "programmatic_access": null
      },
      {
        "state": "OK",
        "county": "Coal",
        "record_type": "will",
        "source_name": "Coal County Probate Records",
        "repository": "Coal County Clerk",
        "access_method": "in_person",
        "url": null,
        "year_start": 1907,
        "year_end": 2024,
        "coverage_notes": "Wills and estate records",
        "survival_notes": null,
        "kinlore_priority": 1,
        "programmatic_access": "FamilySearch API"
      },
      {
        "state": "OK",
        "county": "Coal",
        "record_type": "tribal_record",
        "source_name": "Dawes Rolls (Choctaw)",
        "repository": "Oklahoma Historical Society",
        "access_method": "web_free",
        "url": "https://okhistory.org/research/dawes",
        "year_start": 1898,
        "year_end": 1914,
        "coverage_notes": "Complete Dawes enrollment for Choctaw Nation",
        "survival_notes": "Essential for Coal County Choctaw research",
        "kinlore_priority": 1,
        "programmatic_access": "FamilySearch API"
      },
      {
        "state": "OK",
        "county": "Coal",
        "record_type": "tribal_record",
        "source_name": "Choctaw Nation Vital Records",
        "repository": "Oklahoma Historical Society / FamilySearch",
        "access_method": "web_free",
        "url": "https://www.familysearch.org/search/collection/2077688",
        "year_start": 1851,
        "year_end": 1914,
        "coverage_notes": "Choctaw tribal records",
        "survival_notes": null,
        "kinlore_priority": 2,
        "programmatic_access": "FamilySearch API"
      },
      {
        "state": "OK",
        "county": "Coal",
        "record_type": "marriage",
        "source_name": "Coal County Marriage Records",
        "repository": "Coal County Clerk",
        "access_method": "in_person",
        "url": null,
        "year_start": 1907,
        "year_end": 2024,
        "coverage_notes": "Marriage licenses from statehood",
        "survival_notes": null,
        "kinlore_priority": 1,
        "programmatic_access": "FamilySearch API"
      },
      {
        "state": "OK",
        "county": "Coal",
        "record_type": "birth_death",
        "source_name": "Coal County Vital Records",
        "repository": "Oklahoma State Department of Health",
        "access_method": "web_subscription",
        "url": "https://www.ok.gov/health/",
        "year_start": 1908,
        "year_end": 1924,
        "coverage_notes": "Early vital records",
        "survival_notes": "Incomplete coverage",
        "kinlore_priority": 2,
        "programmatic_access": null
      }
    ]
  },
  {
    "county_metadata": {
      "state": "OK",
      "county": "Comanche",
      "fips_code": "40025",
      "formed_year": 1907,
      "parent_county": "Indian Territory (Comanche/Kiowa/Apache lands)",
      "grandparent_county": null,
      "county_seat": "Lawton",
      "is_burned_county": false,
      "record_losses": null,
      "jurisdictional_notes": "Comanche/Kiowa jurisdiction. Land allotments apply.",
      "research_tips": "Land allotment records. Comanche/Kiowa tribal records at OHS. County records from 1907.",
      "rod_online_url": "https://www.comanchecountyclerk.org/",
      "rod_earliest_deed_year": 1907,
      "rod_online_scope": "Deeds from 1907 forward",
      "heritage_book": null
    },
    "source_profiles": [
      {
        "state": "OK",
        "county": "Comanche",
        "record_type": "deed",
        "source_name": "Comanche County Deed Records",
        "repository": "Comanche County Clerk",
        "access_method": "in_person",
        "url": null,
        "year_start": 1907,
        "year_end": 2024,
        "coverage_notes": "Deeds from statehood",
        "survival_notes": null,
        "kinlore_priority": 1,
        "programmatic_access": null
      },
      {
        "state": "OK",
        "county": "Comanche",
        "record_type": "will",
        "source_name": "Comanche County Probate Records",
        "repository": "Comanche County Clerk",
        "access_method": "in_person",
        "url": null,
        "year_start": 1907,
        "year_end": 2024,
        "coverage_notes": "Wills and estate records",
        "survival_notes": null,
        "kinlore_priority": 1,
        "programmatic_access": "FamilySearch API"
      },
      {
        "state": "OK",
        "county": "Comanche",
        "record_type": "land_grant",
        "source_name": "Comanche/Kiowa Allotment Records",
        "repository": "Oklahoma Historical Society / Bureau of Indian Affairs",
        "access_method": "in_person",
        "url": null,
        "year_start": 1901,
        "year_end": 1914,
        "coverage_notes": "Land allotments for Comanche and Kiowa tribes",
        "survival_notes": "Critical for Comanche County tribal research",
        "kinlore_priority": 2,
        "programmatic_access": null
      },
      {
        "state": "OK",
        "county": "Comanche",
        "record_type": "marriage",
        "source_name": "Comanche County Marriage Records",
        "repository": "Comanche County Clerk",
        "access_method": "in_person",
        "url": null,
        "year_start": 1907,
        "year_end": 2024,
        "coverage_notes": "Marriage licenses from statehood",
        "survival_notes": null,
        "kinlore_priority": 1,
        "programmatic_access": "FamilySearch API"
      },
      {
        "state": "OK",
        "county": "Comanche",
        "record_type": "tribal_record",
        "source_name": "Indian Census Rolls (Comanche/Kiowa)",
        "repository": "Bureau of Indian Affairs / FamilySearch",
        "access_method": "web_free",
        "url": "https://www.familysearch.org",
        "year_start": 1885,
        "year_end": 1940,
        "coverage_notes": "BIA census rolls for tribal populations",
        "survival_notes": null,
        "kinlore_priority": 2,
        "programmatic_access": "FamilySearch API"
      },
      {
        "state": "OK",
        "county": "Comanche",
        "record_type": "birth_death",
        "source_name": "Comanche County Vital Records",
        "repository": "Oklahoma State Department of Health",
        "access_method": "web_subscription",
        "url": "https://www.ok.gov/health/",
        "year_start": 1908,
        "year_end": 1924,
        "coverage_notes": "Early vital records",
        "survival_notes": "Incomplete coverage",
        "kinlore_priority": 2,
        "programmatic_access": null
      }
    ]
  },
  {
    "county_metadata": {
      "state": "OK",
      "county": "Cotton",
      "fips_code": "40027",
      "formed_year": 1907,
      "parent_county": "Indian Territory (Comanche/Kiowa lands)",
      "grandparent_county": null,
      "county_seat": "Walters",
      "is_burned_county": false,
      "record_losses": null,
      "jurisdictional_notes": "Comanche/Kiowa jurisdiction. Land allotments apply.",
      "research_tips": "Land allotment records. Comanche/Kiowa tribal records. County records from 1907.",
      "rod_online_url": null,
      "rod_earliest_deed_year": 1907,
      "rod_online_scope": "Deeds from 1907 forward",
      "heritage_book": null
    },
    "source_profiles": [
      {
        "state": "OK",
        "county": "Cotton",
        "record_type": "deed",
        "source_name": "Cotton County Deed Records",
        "repository": "Cotton County Clerk",
        "access_method": "in_person",
        "url": null,
        "year_start": 1907,
        "year_end": 2024,
        "coverage_notes": "Deeds from statehood",
        "survival_notes": null,
        "kinlore_priority": 1,
        "programmatic_access": null
      },
      {
        "state": "OK",
        "county": "Cotton",
        "record_type": "will",
        "source_name": "Cotton County Probate Records",
        "repository": "Cotton County Clerk",
        "access_method": "in_person",
        "url": null,
        "year_start": 1907,
        "year_end": 2024,
        "coverage_notes": "Wills and estate records",
        "survival_notes": null,
        "kinlore_priority": 1,
        "programmatic_access": "FamilySearch API"
      },
      {
        "state": "OK",
        "county": "Cotton",
        "record_type": "land_grant",
        "source_name": "Comanche/Kiowa Allotment Records",
        "repository": "Oklahoma Historical Society / Bureau of Indian Affairs",
        "access_method": "in_person",
        "url": null,
        "year_start": 1901,
        "year_end": 1914,
        "coverage_notes": "Land allotments for Comanche and Kiowa tribes",
        "survival_notes": "Important for Cotton County tribal research",
        "kinlore_priority": 2,
        "programmatic_access": null
      },
      {
        "state": "OK",
        "county": "Cotton",
        "record_type": "marriage",
        "source_name": "Cotton County Marriage Records",
        "repository": "Cotton County Clerk",
        "access_method": "in_person",
        "url": null,
        "year_start": 1907,
        "year_end": 2024,
        "coverage_notes": "Marriage licenses from statehood",
        "survival_notes": null,
        "kinlore_priority": 1,
        "programmatic_access": "FamilySearch API"
      },
      {
        "state": "OK",
        "county": "Cotton",
        "record_type": "birth_death",
        "source_name": "Cotton County Vital Records",
        "repository": "Oklahoma State Department of Health",
        "access_method": "web_subscription",
        "url": "https://www.ok.gov/health/",
        "year_start": 1908,
        "year_end": 1924,
        "coverage_notes": "Early vital records",
        "survival_notes": "Incomplete coverage",
        "kinlore_priority": 2,
        "programmatic_access": null
      },
      {
        "state": "OK",
        "county": "Cotton",
        "record_type": "tribal_record",
        "source_name": "Indian Census Rolls (Comanche/Kiowa)",
        "repository": "Bureau of Indian Affairs / FamilySearch",
        "access_method": "web_free",
        "url": "https://www.familysearch.org",
        "year_start": 1885,
        "year_end": 1940,
        "coverage_notes": "BIA census rolls",
        "survival_notes": null,
        "kinlore_priority": 2,
        "programmatic_access": "FamilySearch API"
      }
    ]
  },
  {
    "county_metadata": {
      "state": "OK",
      "county": "Craig",
      "fips_code": "40029",
      "formed_year": 1907,
      "parent_county": "Indian Territory (Missouri, Kansas, and Texas - MKT lands)",
      "grandparent_county": null,
      "county_seat": "Vinita",
      "is_burned_county": false,
      "record_losses": null,
      "jurisdictional_notes": "Cherokee Nation and Osage Nation jurisdiction. Dawes Rolls apply.",
      "research_tips": "Cherokee/Osage Dawes Rolls at OHS. County records from 1907.",
      "rod_online_url": null,
      "rod_earliest_deed_year": 1907,
      "rod_online_scope": "Deeds from 1907 forward",
      "heritage_book": null
    },
    "source_profiles": [
      {
        "state": "OK",
        "county": "Craig",
        "record_type": "deed",
        "source_name": "Craig County Deed Records",
        "repository": "Craig County Clerk",
        "access_method": "in_person",
        "url": null,
        "year_start": 1907,
        "year_end": 2024,
        "coverage_notes": "Deeds from statehood",
        "survival_notes": null,
        "kinlore_priority": 1,
        "programmatic_access": null
      },
      {
        "state": "OK",
        "county": "Craig",
        "record_type": "will",
        "source_name": "Craig County Probate Records",
        "repository": "Craig County Clerk",
        "access_method": "in_person",
        "url": null,
        "year_start": 1907,
        "year_end": 2024,
        "coverage_notes": "Wills and estate records",
        "survival_notes": null,
        "kinlore_priority": 1,
        "programmatic_access": "FamilySearch API"
      },
      {
        "state": "OK",
        "county": "Craig",
        "record_type": "tribal_record",
        "source_name": "Dawes Rolls (Cherokee/Osage)",
        "repository": "Oklahoma Historical Society",
        "access_method": "web_free",
        "url": "https://okhistory.org/research/dawes",
        "year_start": 1898,
        "year_end": 1914,
        "coverage_notes": "Dawes enrollment for Cherokee and Osage tribes",
        "survival_notes": "Critical for Craig County tribal ancestry",
        "kinlore_priority": 1,
        "programmatic_access": "FamilySearch API"
      },
      {
        "state": "OK",
        "county": "Craig",
        "record_type": "marriage",
        "source_name": "Craig County Marriage Records",
        "repository": "Craig County Clerk",
        "access_method": "in_person",
        "url": null,
        "year_start": 1907,
        "year_end": 2024,
        "coverage_notes": "Marriage licenses from statehood",
        "survival_notes": null,
        "kinlore_priority": 1,
        "programmatic_access": "FamilySearch API"
      },
      {
        "state": "OK",
        "county": "Craig",
        "record_type": "tribal_record",
        "source_name": "Cherokee/Osage Vital Records",
        "repository": "Oklahoma Historical Society / FamilySearch",
        "access_method": "web_free",
        "url": "https://www.familysearch.org",
        "year_start": 1851,
        "year_end": 1914,
        "coverage_notes": "Tribal enrollment and related records",
        "survival_notes": null,
        "kinlore_priority": 2,
        "programmatic_access": "FamilySearch API"
      },
      {
        "state": "OK",
        "county": "Craig",
        "record_type": "birth_death",
        "source_name": "Craig County Vital Records",
        "repository": "Oklahoma State Department of Health",
        "access_method": "web_subscription",
        "url": "https://www.ok.gov/health/",
        "year_start": 1908,
        "year_end": 1924,
        "coverage_notes": "Early vital records",
        "survival_notes": "Incomplete coverage",
        "kinlore_priority": 2,
        "programmatic_access": null
      }
    ]
  },
  {
    "county_metadata": {
      "state": "OK",
      "county": "Creek",
      "fips_code": "40031",
      "formed_year": 1907,
      "parent_county": "Indian Territory (Muscogee Creek Nation)",
      "grandparent_county": null,
      "county_seat": "Muskogee",
      "is_burned_county": false,
      "record_losses": null,
      "jurisdictional_notes": "Muscogee Creek Nation jurisdiction. Dawes Rolls (Creek) apply.",
      "research_tips": "Creek Dawes Rolls at OHS. Creek tribal records. County records from 1907.",
      "rod_online_url": "https://www.muskogee.us/clerk/",
      "rod_earliest_deed_year": 1907,
      "rod_online_scope": "Deeds from 1907 forward",
      "heritage_book": null
    },
    "source_profiles": [
      {
        "state": "OK",
        "county": "Creek",
        "record_type": "deed",
        "source_name": "Creek County Deed Records",
        "repository": "Creek County Clerk",
        "access_method": "in_person",
        "url": null,
        "year_start": 1907,
        "year_end": 2024,
        "coverage_notes": "Deeds from statehood",
        "survival_notes": null,
        "kinlore_priority": 1,
        "programmatic_access": null
      },
      {
        "state": "OK",
        "county": "Creek",
        "record_type": "will",
        "source_name": "Creek County Probate Records",
        "repository": "Creek County Clerk",
        "access_method": "in_person",
        "url": null,
        "year_start": 1907,
        "year_end": 2024,
        "coverage_notes": "Wills and estate records",
        "survival_notes": null,
        "kinlore_priority": 1,
        "programmatic_access": "FamilySearch API"
      },
      {
        "state": "OK",
        "county": "Creek",
        "record_type": "tribal_record",
        "source_name": "Dawes Rolls (Muscogee Creek)",
        "repository": "Oklahoma Historical Society",
        "access_method": "web_free",
        "url": "https://okhistory.org/research/dawes",
        "year_start": 1898,
        "year_end": 1914,
        "coverage_notes": "Complete Dawes enrollment for Muscogee Creek Nation",
        "survival_notes": "Essential for Creek County Creek ancestry",
        "kinlore_priority": 1,
        "programmatic_access": "FamilySearch API"
      },
      {
        "state": "OK",
        "county": "Creek",
        "record_type": "tribal_record",
        "source_name": "Creek Nation Vital Records",
        "repository": "Oklahoma Historical Society / FamilySearch",
        "access_method": "web_free",
        "url": "https://www.familysearch.org/search/collection/2077734",
        "year_start": 1851,
        "year_end": 1914,
        "coverage_notes": "Creek tribal enrollment and related records",
        "survival_notes": null,
        "kinlore_priority": 2,
        "programmatic_access": "FamilySearch API"
      },
      {
        "state": "OK",
        "county": "Creek",
        "record_type": "marriage",
        "source_name": "Creek County Marriage Records",
        "repository": "Creek County Clerk",
        "access_method": "in_person",
        "url": null,
        "year_start": 1907,
        "year_end": 2024,
        "coverage_notes": "Marriage licenses from statehood",
        "survival_notes": null,
        "kinlore_priority": 1,
        "programmatic_access": "FamilySearch API"
      },
      {
        "state": "OK",
        "county": "Creek",
        "record_type": "birth_death",
        "source_name": "Creek County Vital Records",
        "repository": "Oklahoma State Department of Health",
        "access_method": "web_subscription",
        "url": "https://www.ok.gov/health/",
        "year_start": 1908,
        "year_end": 1924,
        "coverage_notes": "Early vital records",
        "survival_notes": "Incomplete coverage",
        "kinlore_priority": 2,
        "programmatic_access": null
      }
    ]
  },
  {
    "county_metadata": {
      "state": "OK",
      "county": "Custer",
      "fips_code": "40033",
      "formed_year": 1907,
      "parent_county": "Oklahoma Territory",
      "grandparent_county": null,
      "county_seat": "Arapaho",
      "is_burned_county": false,
      "record_losses": null,
      "jurisdictional_notes": "Oklahoma Territory jurisdiction. Cheyenne-Arapaho lands ceded.",
      "research_tips": "Land allotment records. Cheyenne-Arapaho tribal records. County records from 1907.",
      "rod_online_url": null,
      "rod_earliest_deed_year": 1907,
      "rod_online_scope": "Deeds from 1907 forward",
      "heritage_book": null
    },
    "source_profiles": [
      {
        "state": "OK",
        "county": "Custer",
        "record_type": "deed",
        "source_name": "Custer County Deed Records",
        "repository": "Custer County Clerk",
        "access_method": "in_person",
        "url": null,
        "year_start": 1907,
        "year_end": 2024,
        "coverage_notes": "Deeds from statehood",
        "survival_notes": null,
        "kinlore_priority": 1,
        "programmatic_access": null
      },
      {
        "state": "OK",
        "county": "Custer",
        "record_type": "will",
        "source_name": "Custer County Probate Records",
        "repository": "Custer County Clerk",
        "access_method": "in_person",
        "url": null,
        "year_start": 1907,
        "year_end": 2024,
        "coverage_notes": "Wills and estate records",
        "survival_notes": null,
        "kinlore_priority": 1,
        "programmatic_access": "FamilySearch API"
      },
      {
        "state": "OK",
        "county": "Custer",
        "record_type": "land_grant",
        "source_name": "Cheyenne-Arapaho Allotment Records",
        "repository": "Oklahoma Historical Society / Bureau of Indian Affairs",
        "access_method": "in_person",
        "url": null,
        "year_start": 1901,
        "year_end": 1914,
        "coverage_notes": "Land allotments for Cheyenne and Arapaho tribes",
        "survival_notes": "Important for Custer County tribal research",
        "kinlore_priority": 2,
        "programmatic_access": null
      },
      {
        "state": "OK",
        "county": "Custer",
        "record_type": "marriage",
        "source_name": "Custer County Marriage Records",
        "repository": "Custer County Clerk",
        "access_method": "in_person",
        "url": null,
        "year_start": 1907,
        "year_end": 2024,
        "coverage_notes": "Marriage licenses from statehood",
        "survival_notes": null,
        "kinlore_priority": 1,
        "programmatic_access": "FamilySearch API"
      },
      {
        "state": "OK",
        "county": "Custer",
        "record_type": "birth_death",
        "source_name": "Custer County Vital Records",
        "repository": "Oklahoma State Department of Health",
        "access_method": "web_subscription",
        "url": "https://www.ok.gov/health/",
        "year_start": 1908,
        "year_end": 1924,
        "coverage_notes": "Early vital records",
        "survival_notes": "Incomplete coverage",
        "kinlore_priority": 2,
        "programmatic_access": null
      },
      {
        "state": "OK",
        "county": "Custer",
        "record_type": "census",
        "source_name": "1900 Census - Oklahoma Territory",
        "repository": "FamilySearch / Ancestry",
        "access_method": "web_subscription",
        "url": "https://www.familysearch.org",
        "year_start": 1900,
        "year_end": 1900,
        "coverage_notes": "Pre-statehood census",
        "survival_notes": null,
        "kinlore_priority": 2,
        "programmatic_access": "FamilySearch API"
      }
    ]
  },
  {
    "county_metadata": {
      "state": "OK",
      "county": "Delaware",
      "fips_code": "40035",
      "formed_year": 1907,
      "parent_county": "Indian Territory (Cherokee Nation)",
      "grandparent_county": null,
      "county_seat": "Jay",
      "is_burned_county": false,
      "record_losses": null,
      "jurisdictional_notes": "Cherokee Nation jurisdiction. Dawes Rolls (Cherokee) apply.",
      "research_tips": "Cherokee Dawes Rolls at OHS. County records from 1907.",
      "rod_online_url": null,
      "rod_earliest_deed_year": 1907,
      "rod_online_scope": "Deeds from 1907 forward",
      "heritage_book": null
    },
    "source_profiles": [
      {
        "state": "OK",
        "county": "Delaware",
        "record_type": "deed",
        "source_name": "Delaware County Deed Records",
        "repository": "Delaware County Clerk",
        "access_method": "in_person",
        "url": null,
        "year_start": 1907,
        "year_end": 2024,
        "coverage_notes": "Deeds from statehood",
        "survival_notes": null,
        "kinlore_priority": 1,
        "programmatic_access": null
      },
      {
        "state": "OK",
        "county": "Delaware",
        "record_type": "will",
        "source_name": "Delaware County Probate Records",
        "repository": "Delaware County Clerk",
        "access_method": "in_person",
        "url": null,
        "year_start": 1907,
        "year_end": 2024,
        "coverage_notes": "Wills and estate records",
        "survival_notes": null,
        "kinlore_priority": 1,
        "programmatic_access": "FamilySearch API"
      },
      {
        "state": "OK",
        "county": "Delaware",
        "record_type": "tribal_record",
        "source_name": "Dawes Rolls (Cherokee)",
        "repository": "Oklahoma Historical Society",
        "access_method": "web_free",
        "url": "https://okhistory.org/research/dawes",
        "year_start": 1898,
        "year_end": 1914,
        "coverage_notes": "Complete Dawes enrollment for Cherokee Nation",
        "survival_notes": "Essential for Delaware County Cherokee research",
        "kinlore_priority": 1,
        "programmatic_access": "FamilySearch API"
      },
      {
        "state": "OK",
        "county": "Delaware",
        "record_type": "tribal_record",
        "source_name": "Cherokee Nation Vital Records",
        "repository": "Oklahoma Historical Society / FamilySearch",
        "access_method": "web_free",
        "url": "https://www.familysearch.org/search/collection/2077608",
        "year_start": 1851,
        "year_end": 1914,
        "coverage_notes": "Cherokee tribal records",
        "survival_notes": null,
        "kinlore_priority": 2,
        "programmatic_access": "FamilySearch API"
      },
      {
        "state": "OK",
        "county": "Delaware",
        "record_type": "marriage",
        "source_name": "Delaware County Marriage Records",
        "repository": "Delaware County Clerk",
        "access_method": "in_person",
        "url": null,
        "year_start": 1907,
        "year_end": 2024,
        "coverage_notes": "Marriage licenses from statehood",
        "survival_notes": null,
        "kinlore_priority": 1,
        "programmatic_access": "FamilySearch API"
      },
      {
        "state": "OK",
        "county": "Delaware",
        "record_type": "birth_death",
        "source_name": "Delaware County Vital Records",
        "repository": "Oklahoma State Department of Health",
        "access_method": "web_subscription",
        "url": "https://www.ok.gov/health/",
        "year_start": 1908,
        "year_end": 1924,
        "coverage_notes": "Early vital records",
        "survival_notes": "Incomplete coverage",
        "kinlore_priority": 2,
        "programmatic_access": null
      }
    ]
  },
  {
    "county_metadata": {
      "state": "OK",
      "county": "Dewey",
      "fips_code": "40037",
      "formed_year": 1907,
      "parent_county": "Oklahoma Territory",
      "grandparent_county": null,
      "county_seat": "Taloga",
      "is_burned_county": false,
      "record_losses": null,
      "jurisdictional_notes": "Oklahoma Territory jurisdiction. Cheyenne-Arapaho lands ceded.",
      "research_tips": "Land allotment records. County records from 1907.",
      "rod_online_url": null,
      "rod_earliest_deed_year": 1907,
      "rod_online_scope": "Deeds from 1907 forward",
      "heritage_book": null
    },
    "source_profiles": [
      {
        "state": "OK",
        "county": "Dewey",
        "record_type": "deed",
        "source_name": "Dewey County Deed Records",
        "repository": "Dewey County Clerk",
        "access_method": "in_person",
        "url": null,
        "year_start": 1907,
        "year_end": 2024,
        "coverage_notes": "Deeds from statehood",
        "survival_notes": null,
        "kinlore_priority": 1,
        "programmatic_access": null
      },
      {
        "state": "OK",
        "county": "Dewey",
        "record_type": "will",
        "source_name": "Dewey County Probate Records",
        "repository": "Dewey County Clerk",
        "access_method": "in_person",
        "url": null,
        "year_start": 1907,
        "year_end": 2024,
        "coverage_notes": "Wills and estate records",
        "survival_notes": null,
        "kinlore_priority": 1,
        "programmatic_access": "FamilySearch API"
      },
      {
        "state": "OK",
        "county": "Dewey",
        "record_type": "land_grant",
        "source_name": "Cheyenne-Arapaho Allotment Records",
        "repository": "Oklahoma Historical Society / Bureau of Indian Affairs",
        "access_method": "in_person",
        "url": null,
        "year_start": 1901,
        "year_end": 1914,
        "coverage_notes": "Land allotments for Cheyenne and Arapaho tribes",
        "survival_notes": "Important for Dewey County research",
        "kinlore_priority": 2,
        "programmatic_access": null
      },
      {
        "state": "OK",
        "county": "Dewey",
        "record_type": "marriage",
        "source_name": "Dewey County Marriage Records",
        "repository": "Dewey County Clerk",
        "access_method": "in_person",
        "url": null,
        "year_start": 1907,
        "year_end": 2024,
        "coverage_notes": "Marriage licenses from statehood",
        "survival_notes": null,
        "kinlore_priority": 1,
        "programmatic_access": "FamilySearch API"
      },
      {
        "state": "OK",
        "county": "Dewey",
        "record_type": "census",
        "source_name": "1900 Census - Oklahoma Territory",
        "repository": "FamilySearch / Ancestry",
        "access_method": "web_subscription",
        "url": "https://www.familysearch.org",
        "year_start": 1900,
        "year_end": 1900,
        "coverage_notes": "Pre-statehood census",
        "survival_notes": null,
        "kinlore_priority": 2,
        "programmatic_access": "FamilySearch API"
      },
      {
        "state": "OK",
        "county": "Dewey",
        "record_type": "birth_death",
        "source_name": "Dewey County Vital Records",
        "repository": "Oklahoma State Department of Health",
        "access_method": "web_subscription",
        "url": "https://www.ok.gov/health/",
        "year_start": 1908,
        "year_end": 1924,
        "coverage_notes": "Early vital records",
        "survival_notes": "Incomplete coverage",
        "kinlore_priority": 2,
        "programmatic_access": null
      }
    ]
  },
  {
    "county_metadata": {
      "state": "OK",
      "county": "Ellis",
      "fips_code": "40039",
      "formed_year": 1907,
      "parent_county": "Oklahoma Territory",
      "grandparent_county": null,
      "county_seat": "Arnett",
      "is_burned_county": false,
      "record_losses": null,
      "jurisdictional_notes": "Oklahoma Territory jurisdiction. No tribal jurisdiction.",
      "research_tips": "Land Run records (1889). County records from 1907.",
      "rod_online_url": null,
      "rod_earliest_deed_year": 1907,
      "rod_online_scope": "Deeds from 1907 forward",
      "heritage_book": null
    },
    "source_profiles": [
      {
        "state": "OK",
        "county": "Ellis",
        "record_type": "deed",
        "source_name": "Ellis County Deed Records",
        "repository": "Ellis County Clerk",
        "access_method": "in_person",
        "url": null,
        "year_start": 1907,
        "year_end": 2024,
        "coverage_notes": "Deeds from statehood",
        "survival_notes": null,
        "kinlore_priority": 1,
        "programmatic_access": null
      },
      {
        "state": "OK",
        "county": "Ellis",
        "record_type": "will",
        "source_name": "Ellis County Probate Records",
        "repository": "Ellis County Clerk",
        "access_method": "in_person",
        "url": null,
        "year_start": 1907,
        "year_end": 2024,
        "coverage_notes": "Wills and estate records",
        "survival_notes": null,
        "kinlore_priority": 1,
        "programmatic_access": "FamilySearch API"
      },
      {
        "state": "OK",
        "county": "Ellis",
        "record_type": "land_grant",
        "source_name": "Oklahoma Land Run Records (1889)",
        "repository": "Oklahoma Historical Society",
        "access_method": "web_free",
        "url": "https://okhistory.org/research/landrun",
        "year_start": 1889,
        "year_end": 1889,
        "coverage_notes": "Land Run claims for Oklahoma Territory",
        "survival_notes": null,
        "kinlore_priority": 2,
        "programmatic_access": null
      },
      {
        "state": "OK",
        "county": "Ellis",
        "record_type": "marriage",
        "source_name": "Ellis County Marriage Records",
        "repository": "Ellis County Clerk",
        "access_method": "in_person",
        "url": null,
        "year_start": 1907,
        "year_end": 2024,
        "coverage_notes": "Marriage licenses from statehood",
        "survival_notes": null,
        "kinlore_priority": 1,
        "programmatic_access": "FamilySearch API"
      },
      {
        "state": "OK",
        "county": "Ellis",
        "record_type": "census",
        "source_name": "1900 Census - Oklahoma Territory",
        "repository": "FamilySearch / Ancestry",
        "access_method": "web_subscription",
        "url": "https://www.familysearch.org",
        "year_start": 1900,
        "year_end": 1900,
        "coverage_notes": "Pre-statehood census",
        "survival_notes": null,
        "kinlore_priority": 2,
        "programmatic_access": "FamilySearch API"
      },
      {
        "state": "OK",
        "county": "Ellis",
        "record_type": "birth_death",
        "source_name": "Ellis County Vital Records",
        "repository": "Oklahoma State Department of Health",
        "access_method": "web_subscription",
        "url": "https://www.ok.gov/health/",
        "year_start": 1908,
        "year_end": 1924,
        "coverage_notes": "Early vital records",
        "survival_notes": "Incomplete coverage",
        "kinlore_priority": 2,
        "programmatic_access": null
      }
    ]
  },
  {
    "county_metadata": {
      "state": "OK",
      "county": "Garfield",
      "fips_code": "40041",
      "formed_year": 1907,
      "parent_county": "Oklahoma Territory",
      "grandparent_county": null,
      "county_seat": "Enid",
      "is_burned_county": false,
      "record_losses": null,
      "jurisdictional_notes": "Oklahoma Territory jurisdiction. No tribal jurisdiction.",
      "research_tips": "Land Run records (1889). County records from 1907.",
      "rod_online_url": "https://www.garfieldcountyclerk.org/",
      "rod_earliest_deed_year": 1907,
      "rod_online_scope": "Deeds from 1907 forward",
      "heritage_book": null
    },
    "source_profiles": [
      {
        "state": "OK",
        "county": "Garfield",
        "record_type": "deed",
        "source_name": "Garfield County Deed Records",
        "repository": "Garfield County Clerk",
        "access_method": "in_person",
        "url": null,
        "year_start": 1907,
        "year_end": 2024,
        "coverage_notes": "Deeds from statehood",
        "survival_notes": null,
        "kinlore_priority": 1,
        "programmatic_access": null
      },
      {
        "state": "OK",
        "county": "Garfield",
        "record_type": "will",
        "source_name": "Garfield County Probate Records",
        "repository": "Garfield County Clerk",
        "access_method": "in_person",
        "url": null,
        "year_start": 1907,
        "year_end": 2024,
        "coverage_notes": "Wills and estate records",
        "survival_notes": null,
        "kinlore_priority": 1,
        "programmatic_access": "FamilySearch API"
      },
      {
        "state": "OK",
        "county": "Garfield",
        "record_type": "land_grant",
        "source_name": "Oklahoma Land Run Records (1889)",
        "repository": "Oklahoma Historical Society",
        "access_method": "web_free",
        "url": "https://okhistory.org/research/landrun",
        "year_start": 1889,
        "year_end": 1889,
        "coverage_notes": "Land Run claims for Oklahoma Territory",
        "survival_notes": null,
        "kinlore_priority": 2,
        "programmatic_access": null
      },
      {
        "state": "OK",
        "county": "Garfield",
        "record_type": "marriage",
        "source_name": "Garfield County Marriage Records",
        "repository": "Garfield County Clerk",
        "access_method": "in_person",
        "url": null,
        "year_start": 1907,
        "year_end": 2024,
        "coverage_notes": "Marriage licenses from statehood",
        "survival_notes": null,
        "kinlore_priority": 1,
        "programmatic_access": "FamilySearch API"
      },
      {
        "state": "OK",
        "county": "Garfield",
        "record_type": "census",
        "source_name": "1900 Census - Oklahoma Territory",
        "repository": "FamilySearch / Ancestry",
        "access_method": "web_subscription",
        "url": "https://www.familysearch.org",
        "year_start": 1900,
        "year_end": 1900,
        "coverage_notes": "Pre-statehood census",
        "survival_notes": null,
        "kinlore_priority": 2,
        "programmatic_access": "FamilySearch API"
      },
      {
        "state": "OK",
        "county": "Garfield",
        "record_type": "birth_death",
        "source_name": "Garfield County Vital Records",
        "repository": "Oklahoma State Department of Health",
        "access_method": "web_subscription",
        "url": "https://www.ok.gov/health/",
        "year_start": 1908,
        "year_end": 1924,
        "coverage_notes": "Early vital records",
        "survival_notes": "Incomplete coverage",
        "kinlore_priority": 2,
        "programmatic_access": null
      }
    ]
  }
]
